bitfinexget/__init__.py
bitfinexget/bitmex_fundings.py
bitfinexget/tools.py
bitfinexget-0.3.0.dist-info/LICENSE
bitfinexget-0.3.0.dist-info/METADATA
bitfinexget-0.3.0.dist-info/WHEEL
bitfinexget-0.3.0.dist-info/top_level.txt
bitfinexget-0.3.0.dist-info/RECORD
