Metadata-Version: 2.1
Name: bitfinexget
Version: 0.3.0
Summary: A small package to get history, easily download all avaliable history to csv or update current csv files
Home-page: https://github.com/realiti4/bitfinexget
Author: Onur Cetinkol
Author-email: realiti44@gmail.com
License: UNKNOWN
Platform: UNKNOWN
Classifier: Programming Language :: Python :: 3
Classifier: License :: OSI Approved :: MIT License
Classifier: Operating System :: OS Independent
Requires-Python: >=3.6
Requires-Dist: pandas
Requires-Dist: requests
